src/execute/alu.v
// update the flags register and do the required calculations
module alu(
    input wire clk,
    input wire [12:0] alusignals,
    /*
        isadd
        isld
        isst
        issub
        ismul
        iscmp
        ismov
        isor
        isand
        isnot
        islsl
        islsr
        isxor
    */
    input wire [15:0] op1,
    input wire [15:0] op2,
    input wire [4:0] immx,
    input wire isimmediate,
    output reg [15:0] aluresult
);
    integer file;
    integer i;
    reg [15:0] reg_file [7:0];
    wire [15:0] A = op1;
    wire [15:0] B = isimmediate ? immx : op2;
    wire isadd = alusignals[0];
    wire isld = alusignals[1];
    wire isst = alusignals[2];
    wire issub = alusignals[3];
    wire ismul = alusignals[4];
    wire iscmp = alusignals[5];
    wire ismov = alusignals[6];
    wire isor = alusignals[7];
    wire isand = alusignals[8];
    wire isnot = alusignals[9];
    wire islsl = alusignals[10];
    wire islsr = alusignals[11];
    wire isxor = alusignals[12];
    reg [15:0] result;
    initial begin
        $readmemh("registers.hex", reg_file);
    end
    always @(posedge clk) begin
        if (isadd) begin
            result <= A + B;
        end else if (isld) begin
            result <= A + B;
        end else if (isst) begin
            result <= A + B;
        end else if (issub) begin
            result <= A - B;
        end else if (ismul) begin
            result <= A * B;
        end else if (iscmp) begin // 1 for equal, 2 for greater than  , 0 for less than 
            result <= A - B;
            if (result == 0) begin
                result <= 16'b1;
                reg_file[7] <= 16'b1;
            end else if (result>0) begin
                result <= 16'b0;
                reg_file[7] <= 16'h2;
            end else begin
                result <= 16'b0;
                reg_file[7] <= 16'h0;
            end
        end else if (ismov) begin
            result <= B;
        end else if (isor) begin
            result <= A | B;
        end else if (isand) begin
            result <= A & B;
        end else if (isnot) begin
            result <= ~A;
        end else if (isxor) begin
            result <= A ^ B;
        end else if (islsl) begin
            result <= A << B;
        end else if (islsr) begin
            result <= A >> B;
        end else begin
            result <= 16'b0;
        end
        
    end
    always @(*) begin
        aluresult <= result;
        if (iscmp) begin
            file = $fopen("registers.hex", "w");
            if (file) begin
                $display("Writing modified data...");
                // Write each modified memory value to the new file
                for (i = 0; i < 8; i = i + 1) begin
                    $fwrite(file, "%h\n", reg_file[i]);  // Write as hexadecimal
                end
                $fclose(file);  // Close the file
                $display("Data written to register file successfully.");
            end else begin
                $display("Error: Could not open file for writing.");
            end
        end
    end
endmodule

tb/alu_tb.v
`timescale 1ns / 1ps

module alu_tb();
    // Inputs
    reg clk;
    reg [12:0] alusignals;
    reg [15:0] op1;
    reg [15:0] op2;
    reg [4:0] immx;
    reg isimmediate;

    // Output
    wire [15:0] aluresult;

    // Instantiate the ALU module
    alu uut (
        .clk(clk),
        .alusignals(alusignals),
        .op1(op1),
        .op2(op2),
        .immx(immx),
        .isimmediate(isimmediate),
        .aluresult(aluresult)
    );

    // Clock generation
    initial begin
        clk = 0;
        forever #5 clk = ~clk; // 10ns clock period
    end

    // Test procedure
    initial begin
        $dumpfile("alu_unit.vcd");
        $dumpvars(0,alu_tb);
        // Initialize inputs
        op1 = 16'h0005;    // Operand 1
        op2 = 16'h0003;    // Operand 2
        immx = 5'b00011;   // Immediate value
        isimmediate = 0;
        alusignals = 12'b000000000000; // Clear ALU signals
        #10;

        // Test ADD operation
        alusignals = 12'b000000000001; // isadd
        #10;
        $display("ADD: Result = %h", aluresult);

        // Test SUB operation
        alusignals = 12'b000000001000; // issub
        #10;
        $display("SUB: Result = %h", aluresult);

        // Test MUL operation
        alusignals = 12'b000000010000; // ismul
        #10;
        $display("MUL: Result = %h", aluresult);

        // Test MOV operation
        alusignals = 12'b000001000000; // ismov
        #10;
        $display("MOV (immediate): Result = %h", aluresult);

        // Test OR operation
        alusignals = 12'b000010000000; // isor
        #10;
        $display("OR: Result = %h", aluresult);

        // Test AND operation
        alusignals = 12'b000100000000; // isand
        #10;
        $display("AND: Result = %h", aluresult);

        // Test NOT operation
        alusignals = 12'b001000000000; // isnot
        #10;
        $display("NOT: Result = %h", aluresult);

        // Test LSL operation
        alusignals = 12'b01000000000; // islsl
        #10;
        $display("LSL: Result = %h", aluresult);

        // Test LSR operation
        alusignals = 12'b10000000000; // islsr
        #10;
        $display("LSR: Result = %h", aluresult);
        
        // Test CMP operation
        alusignals = 12'b000000100000; // iscmp
        #10;
        $display("CMP: Result = %h", aluresult);

        // End of test
        $finish;
    end
endmodule

alu_unit.vcd
$date
	Sat Nov  9 02:42:30 2024
$end
$version
	Icarus Verilog
$end
$timescale
	1ps
$end
$scope module alu_tb $end
$var wire 16 ! aluresult [15:0] $end
$var reg 13 " alusignals [12:0] $end
$var reg 1 # clk $end
$var reg 5 $ immx [4:0] $end
$var reg 1 % isimmediate $end
$var reg 16 & op1 [15:0] $end
$var reg 16 ' op2 [15:0] $end
$scope module uut $end
$var wire 16 ( A [15:0] $end
$var wire 13 ) alusignals [12:0] $end
$var wire 1 # clk $end
$var wire 5 * immx [4:0] $end
$var wire 1 % isimmediate $end
$var wire 16 + op1 [15:0] $end
$var wire 16 , op2 [15:0] $end
$var wire 1 - isxor $end
$var wire 1 . issub $end
$var wire 1 / isst $end
$var wire 1 0 isor $end
$var wire 1 1 isnot $end
$var wire 1 2 ismul $end
$var wire 1 3 ismov $end
$var wire 1 4 islsr $end
$var wire 1 5 islsl $end
$var wire 1 6 isld $end
$var wire 1 7 iscmp $end
$var wire 1 8 isand $end
$var wire 1 9 isadd $end
$var wire 16 : B [15:0] $end
$var reg 16 ; aluresult [15:0] $end
$var reg 16 < result [15:0] $end
$var integer 32 = file [31:0] $end
$var integer 32 > i [31:0] $end
$upscope $end
$upscope $end
$enddefinitions $end
#0
$dumpvars
bx >
bx =
bx <
bx ;
b11 :
09
08
07
06
05
04
03
02
01
00
0/
0.
0-
b11 ,
b101 +
b11 *
b0 )
b101 (
b11 '
b101 &
0%
b11 $
0#
b0 "
bx !
$end
#5000
b0 !
b0 ;
b0 <
1#
#10000
19
0#
b1 "
b1 )
#15000
b1000 !
b1000 ;
b1000 <
1#
#20000
09
1.
0#
b1000 "
b1000 )
#25000
b10 !
b10 ;
b10 <
1#
#30000
0.
12
0#
b10000 "
b10000 )
#35000
b1111 !
b1111 ;
b1111 <
1#
#40000
02
13
0#
b1000000 "
b1000000 )
#45000
b11 !
b11 ;
b11 <
1#
#50000
03
10
0#
b10000000 "
b10000000 )
#55000
b111 !
b111 ;
b111 <
1#
#60000
00
18
0#
b100000000 "
b100000000 )
#65000
b1 !
b1 ;
b1 <
1#
#70000
08
11
0#
b1000000000 "
b1000000000 )
#75000
b1111111111111010 !
b1111111111111010 ;
b1111111111111010 <
1#
#80000
0#
#85000
1#
#90000
01
15
0#
b10000000000 "
b10000000000 )
#95000
b101000 !
b101000 ;
b101000 <
1#
#100000
b1000 >
b10000000000000000000000000000011 =
17
05
0#
b100000 "
b100000 )
#105000
b0 !
b0 ;
b1000 >
b0 <
1#
