src/execute/alu.v
// update the flags register and do the required calculations
module alu(
    input wire clk,
    input wire [11:0] alusignals,
    /*
        isadd
        isld
        isst
        issub
        ismul
        iscmp
        ismov
        isor
        isand
        isnot
        islsl
        islsr
    */
    input wire [15:0] op1,
    input wire [15:0] op2,
    input wire [4:0] immx,
    input wire isimmediate,
    output wire [15:0] aluresult
);
    integer file;
    integer i;
    reg [15:0] reg_file [7:0];
    reg [15:0] A;
    reg [15:0] B;
    wire isadd;
    wire isld;
    wire isst;
    wire issub;
    wire ismul;
    wire iscmp;
    wire ismov;
    wire isor;
    wire isand;
    wire isnot;
    wire islsl;
    wire islsr;
    assign isadd = alusignals[0];
    assign isld = alusignals[1];
    assign isst = alusignals[2];
    assign issub = alusignals[3];
    assign ismul = alusignals[4];
    assign iscmp = alusignals[5];
    assign ismov = alusignals[6];
    assign isor = alusignals[7];
    assign isand = alusignals[8];
    assign isnot = alusignals[9];
    assign islsl = alusignals[10];
    assign islsr = alusignals[11];
    reg isadd_reg;
    reg isld_reg;
    reg isst_reg;
    reg issub_reg;
    reg ismul_reg;
    reg iscmp_reg;
    reg ismov_reg;
    reg isor_reg;
    reg isand_reg;
    reg isnot_reg;
    reg islsl_reg;
    reg islsr_reg;
    reg isimmediate_reg;
    reg [15:0]op1_reg;
    reg [15:0]op2_reg;
    reg [4:0]immx_reg;
    reg [15:0] result;
    initial begin
        $readmemh("registers.hex", reg_file);
        isadd_reg = 1'b0;
        isld_reg = 1'b0;
        isst_reg = 1'b0;
        issub_reg = 1'b0;
        ismul_reg = 1'b0;
        iscmp_reg = 1'b0;
        ismov_reg = 1'b0;
        isor_reg = 1'b0;
        isand_reg = 1'b0;
        isnot_reg = 1'b0;
        islsl_reg = 1'b0;
        islsr_reg = 1'b0;
        isimmediate_reg = 1'b0;
        op1_reg = 16'b0;
        op2_reg = 16'b0;
        immx_reg = 5'b0;
    end
    always @(posedge clk) begin
        if (isimmediate_reg) begin
            A = op1;
            B = immx;
        end else begin
            A = op1;
            B = op2;
        end
        if (isadd_reg) begin
            result <= A + B;
        end else if (isld_reg) begin
            result <= A + B;
        end else if (isst_reg) begin
            result <= A + B;
        end else if (issub_reg) begin
            result <= A - B;
        end else if (ismul_reg) begin
            result <= A * B;
        end else if (iscmp_reg) begin // 1 for equal, 2 for greater than  , 0 for less than 
            if (A == B) begin
                result <= 16'b1;
                reg_file[7] = 16'b1;
            end else if (A>B) begin
                result <= 16'b0;
                reg_file[7] = 16'h2;
            end else begin
                result <= 16'b0;
                reg_file[7] = 16'h0;
            end
            file = $fopen("registers.hex", "w");
            if (file) begin
                $display("Writing modified data...");
                // Write each modified memory value to the new file
                for (i = 0; i < 8; i = i + 1) begin
                    $fwrite(file, "%h\n", reg_file[i]);  // Write as hexadecimal
                    $display("Data written to register file successfully. %h",reg_file[i]);
                end
                $fclose(file);  // Close the file
                $display("Data written to register file successfully.");
            end else begin
                $display("Error: Could not open file for writing.");
            end
        end else if (ismov_reg) begin
            result <= B;
        end else if (isor_reg) begin
            result <= A | B;
        end else if (isand_reg) begin
            result <= A & B;
        end else if (isnot_reg) begin
            result <= ~A;
        end else if (islsl_reg) begin
            result <= A << B;
        end else if (islsr_reg) begin
            result <= A >> B;
        end else begin
            result <= 16'b0;
        end
        isadd_reg <= isadd;
        isld_reg <= isld;
        isst_reg <= isst;
        issub_reg <= issub;
        ismul_reg <= ismul;
        iscmp_reg <= iscmp;
        ismov_reg <= ismov;
        isor_reg <= isor;
        isand_reg <= isand;
        isnot_reg <= isnot;
        islsl_reg <= islsl;
        islsr_reg <= islsr;
        isimmediate_reg <= isimmediate;
        op1_reg <= op1;
        op2_reg <= op2;     
    end
    assign aluresult = result;
endmodule

tb/alu_tb.v
`timescale 1ns / 1ps

module alu_tb();
    // Inputs
    reg clk;
    reg [11:0] alusignals;
    reg [15:0] op1;
    reg [15:0] op2;
    reg [4:0] immx;
    reg isimmediate;

    // Output
    wire [15:0] aluresult;

    // Instantiate the ALU module
    alu uut (
        .clk(clk),
        .alusignals(alusignals),
        .op1(op1),
        .op2(op2),
        .immx(immx),
        .isimmediate(isimmediate),
        .aluresult(aluresult)
    );

    // Clock generation
    initial begin
        clk = 1;
        forever #5 clk = ~clk; // 10ns clock period
    end

    // Test procedure
    initial begin
        $dumpfile("alu_unit.vcd");
        $dumpvars(0,alu_tb);
        // Initialize inputs
        op1 = 16'h0005;    // Operand 1
        op2 = 16'h0003;    // Operand 2
        immx = 5'b00011;   // Immediate value
        isimmediate = 0;
        alusignals = 12'b000000000000; // Clear ALU signals
        #10;

        // Test ADD operation
        alusignals = 12'b000000000001; // isadd
        #10;
        $display("ADD: Result = %h", aluresult);

        // Test LOAD operation
        alusignals = 12'b000000000010; // isld
        #10;
        $display("LOAD: Result = %h", aluresult);

        // Test STORE operation
        alusignals = 12'b000000000100; // isst
        #10;
        $display("STORE: Result = %h", aluresult);
        
        // Test SUB operation
        alusignals = 12'b000000001000; // issub
        #10;
        $display("SUB: Result = %h", aluresult);

        // Test MUL operation
        alusignals = 12'b000000010000; // ismul
        #10;
        $display("MUL: Result = %h", aluresult);

        // Test CMP operation
        alusignals = 12'b000000100000; // iscmp
        #10;
        $display("CMP: Result = %h", aluresult);
        
        // Test MOV operation
        alusignals = 12'b000001000000; // ismov
        #10;
        $display("MOV (immediate): Result = %h", aluresult);

        // Test OR operation
        alusignals = 12'b000010000000; // isor
        #10;
        $display("OR: Result = %h", aluresult);

        // Test AND operation
        alusignals = 12'b000100000000; // isand
        #10;
        $display("AND: Result = %h", aluresult);

        // Test NOT operation
        alusignals = 12'b001000000000; // isnot
        #10;
        $display("NOT: Result = %h", aluresult);

        // Test LSL operation
        alusignals = 12'b010000000000; // islsl
        #10;
        $display("LSL: Result = %h", aluresult);

        // Test LSR operation
        alusignals = 12'b100000000000; // islsr
        #10;
        $display("LSR: Result = %h", aluresult);
        

        #50;
        // End of test
        $finish;
    end
endmodule

alu_unit.vcd
$date
	Sat Nov  9 20:02:45 2024
$end
$version
	Icarus Verilog
$end
$timescale
	1ps
$end
$scope module alu_tb $end
$var wire 16 ! aluresult [15:0] $end
$var reg 12 " alusignals [11:0] $end
$var reg 1 # clk $end
$var reg 5 $ immx [4:0] $end
$var reg 1 % isimmediate $end
$var reg 16 & op1 [15:0] $end
$var reg 16 ' op2 [15:0] $end
$scope module uut $end
$var wire 16 ( aluresult [15:0] $end
$var wire 12 ) alusignals [11:0] $end
$var wire 1 # clk $end
$var wire 5 * immx [4:0] $end
$var wire 1 % isimmediate $end
$var wire 16 + op1 [15:0] $end
$var wire 16 , op2 [15:0] $end
$var wire 1 - issub $end
$var wire 1 . isst $end
$var wire 1 / isor $end
$var wire 1 0 isnot $end
$var wire 1 1 ismul $end
$var wire 1 2 ismov $end
$var wire 1 3 islsr $end
$var wire 1 4 islsl $end
$var wire 1 5 isld $end
$var wire 1 6 iscmp $end
$var wire 1 7 isand $end
$var wire 1 8 isadd $end
$var reg 16 9 A [15:0] $end
$var reg 16 : B [15:0] $end
$var reg 5 ; immx_reg [4:0] $end
$var reg 1 < isadd_reg $end
$var reg 1 = isand_reg $end
$var reg 1 > iscmp_reg $end
$var reg 1 ? isimmediate_reg $end
$var reg 1 @ isld_reg $end
$var reg 1 A islsl_reg $end
$var reg 1 B islsr_reg $end
$var reg 1 C ismov_reg $end
$var reg 1 D ismul_reg $end
$var reg 1 E isnot_reg $end
$var reg 1 F isor_reg $end
$var reg 1 G isst_reg $end
$var reg 1 H issub_reg $end
$var reg 16 I op1_reg [15:0] $end
$var reg 16 J op2_reg [15:0] $end
$var reg 16 K result [15:0] $end
$var integer 32 L file [31:0] $end
$var integer 32 M i [31:0] $end
$upscope $end
$upscope $end
$enddefinitions $end
#0
$dumpvars
bx M
bx L
b0 K
b11 J
b101 I
xH
xG
xF
xE
xD
xC
xB
xA
x@
0?
x>
x=
x<
b0 ;
b11 :
b101 9
08
07
06
05
04
03
02
01
00
0/
0.
0-
b11 ,
b101 +
b11 *
b0 )
b0 (
b11 '
b101 &
0%
b11 $
1#
b0 "
b0 !
$end
#5000
0#
#10000
0B
0A
0E
0=
0F
0C
0>
0D
0H
0G
0@
1<
18
1#
b1 "
b1 )
#15000
0#
#20000
1@
0<
b1000 !
b1000 (
b1000 K
08
15
1#
b10 "
b10 )
#25000
0#
#30000
1G
0@
05
1.
1#
b100 "
b100 )
#35000
0#
#40000
1H
0G
0.
1-
1#
b1000 "
b1000 )
#45000
0#
#50000
1D
0H
b10 !
b10 (
b10 K
0-
11
1#
b10000 "
b10000 )
#55000
0#
#60000
1>
0D
b1111 !
b1111 (
b1111 K
01
16
1#
b100000 "
b100000 )
#65000
0#
#70000
1C
0>
b0 !
b0 (
b0 K
b1000 M
b10000000000000000000000000000011 L
06
12
1#
b1000000 "
b1000000 )
#75000
0#
#80000
1F
0C
b11 !
b11 (
b11 K
02
1/
1#
b10000000 "
b10000000 )
#85000
0#
#90000
1=
0F
b111 !
b111 (
b111 K
0/
17
1#
b100000000 "
b100000000 )
#95000
0#
#100000
1E
0=
b1 !
b1 (
b1 K
07
10
1#
b1000000000 "
b1000000000 )
#105000
0#
#110000
1A
0E
b1111111111111010 !
b1111111111111010 (
b1111111111111010 K
00
14
1#
b10000000000 "
b10000000000 )
#115000
0#
#120000
1B
0A
b101000 !
b101000 (
b101000 K
04
13
1#
b100000000000 "
b100000000000 )
#125000
0#
#130000
b0 !
b0 (
b0 K
1#
