src/execute/alu.v
// update the flags register and do the required calculations
module alu(
    input wire clk,
    input wire [11:0] alusignals,
    /*
        isadd
        isld
        isst
        issub
        ismul
        iscmp
        ismov
        isor
        isand
        isnot
        islsl
        islsr
    */  
    input wire [15:0] op1,
    input wire [15:0] op2,
    input wire [4:0] immx,
    input wire [15:0] instr,
    input wire isimmediate,
    output wire [15:0] aluresult,
    output wire [18:0] rdval
);
    integer file;
    integer i;
    reg [15:0] reg_file [7:0];
    reg [15:0] A;
    reg [15:0] B;
    wire isadd;
    wire isld;
    wire isst;
    wire issub;
    wire ismul;
    wire iscmp;
    wire ismov;
    wire isor;
    wire isand;
    wire isnot;
    wire islsl;
    wire islsr;
    assign isadd = alusignals[0];
    assign isld = alusignals[1];
    assign isst = alusignals[2];
    assign issub = alusignals[3];
    assign ismul = alusignals[4];
    assign iscmp = alusignals[5];
    assign ismov = alusignals[6];
    assign isor = alusignals[7];
    assign isand = alusignals[8];
    assign isnot = alusignals[9];
    assign islsl = alusignals[10];
    assign islsr = alusignals[11];
    reg isadd_reg;
    reg isld_reg;
    reg isst_reg;
    reg issub_reg;
    reg ismul_reg;
    reg iscmp_reg;
    reg ismov_reg;
    reg isor_reg;
    reg isand_reg;
    reg isnot_reg;
    reg islsl_reg;
    reg islsr_reg;
    reg isimmediate_reg;
    reg [15:0]op1_reg;
    reg [15:0]op2_reg;
    reg [4:0]immx_reg;
    reg [15:0] result;
    reg [2:0] rd;
    initial begin
        $readmemh("registers.hex", reg_file);
        isadd_reg = 1'b0;
        isld_reg = 1'b0;
        isst_reg = 1'b0;
        issub_reg = 1'b0;
        ismul_reg = 1'b0;
        iscmp_reg = 1'b0;
        ismov_reg = 1'b0;
        isor_reg = 1'b0;
        isand_reg = 1'b0;
        isnot_reg = 1'b0;
        islsl_reg = 1'b0;
        islsr_reg = 1'b0;
        isimmediate_reg = 1'b0;
        op1_reg = 16'b0;
        op2_reg = 16'b0;
        immx_reg = 5'b0;
        rd = 3'b0;
        instrw = 16'b0;
    end
    reg [15:0] instrw;
    always @(posedge clk) begin
        if (isimmediate_reg) begin
            A = op1;
            B = immx;
        end else begin
            A = op1;
            B = op2;
        end
        if (isadd_reg) begin
            result <= A + B;
        end else if (isld_reg) begin
            result <= A + B;
        end else if (isst_reg) begin
            result <= A + B;
        end else if (issub_reg) begin
            result <= A - B;
        end else if (ismul_reg) begin
            result <= A * B;
        end else if (iscmp_reg) begin // 1 for equal, 2 for greater than  , 0 for less than 
            if (A == B) begin
                result <= 16'b1;
                reg_file[7] = 16'b1;
            end else if (A>B) begin
                result <= 16'b0;
                reg_file[7] = 16'h2;
            end else begin
                result <= 16'b0;
                reg_file[7] = 16'h0;
            end
            file = $fopen("registers.hex", "w");
            if (file) begin
                $display("Writing modified data...");
                // Write each modified memory value to the new file
                for (i = 0; i < 8; i = i + 1) begin
                    $fwrite(file, "%h\n", reg_file[i]);  // Write as hexadecimal
                    $display("Data written to register file successfully. %h",reg_file[i]);
                end
                $fclose(file);  // Close the file
                $display("Data written to register file successfully.");
            end else begin
                $display("Error: Could not open file for writing.");
            end
        end else if (ismov_reg) begin
            result <= B;
        end else if (isor_reg) begin
            result <= A | B;
        end else if (isand_reg) begin
            result <= A & B;
        end else if (isnot_reg) begin
            result <= ~A;
        end else if (islsl_reg) begin
            result <= A << B;
        end else if (islsr_reg) begin
            result <= A >> B;
        end else begin
            result <= 16'b0;
        end
        isadd_reg <= isadd;
        isld_reg <= isld;
        isst_reg <= isst;
        issub_reg <= issub;
        ismul_reg <= ismul;
        iscmp_reg <= iscmp;
        ismov_reg <= ismov;
        isor_reg <= isor;
        isand_reg <= isand;
        isnot_reg <= isnot;
        islsl_reg <= islsl;
        islsr_reg <= islsr;
        isimmediate_reg <= isimmediate;
        op1_reg <= op1;
        op2_reg <= op2;    
        instrw <= instr[10:8];
        rd<=instrw;
    end
    assign aluresult = result;
    assign rdval = {result,rd};
endmodule

tb/alu_tb.v

module alu_tb;

    reg clk;
    reg [11:0] alusignals;
    reg [15:0] op1;
    reg [15:0] op2;
    reg [4:0] immx;
    reg [15:0] instr;
    reg isimmediate;
    wire [15:0] aluresult;
    wire [18:0] rdval;

    // Instantiate the ALU module
    alu uut (
        .clk(clk),
        .alusignals(alusignals),
        .op1(op1),
        .op2(op2),
        .immx(immx),
        .instr(instr),
        .isimmediate(isimmediate),
        .aluresult(aluresult),
        .rdval(rdval)
    );

    // Clock generation
    initial begin
        clk = 0;
        forever #5 clk = ~clk;  // 10 ns clock period
    end

    // Test initialization
    initial begin
        $dumpfile("alu_tb.vcd");
        $dumpvars(0, alu_tb);
        $monitor("Time = %0d, op1 = %h, op2 = %h, immx = %h, aluresult = %h, rdval = %h", 
                  $time, op1, op2, immx, aluresult, rdval);
        #5
        // Reset inputs
        alusignals = 12'b0;
        op1 = 16'b0;
        op2 = 16'b0;
        immx = 5'b0;
        instr = 16'b0;
        isimmediate = 0;

        // Wait for reset to settle
        #10;
        // Test ADD operation
        op1 = 16'h0010;
        op2 = 16'h0005;
        alusignals = 12'b000000000001; // Setting `isadd` high
        #10;
        
        // Test SUB operation
        alusignals = 12'b000000000010; // Setting `issub` high
        #10;

        // Test MUL operation
        alusignals = 12'b000000001000; // Setting `ismul` high
        #10;

        // Test OR operation
        alusignals = 12'b000000010000; // Setting `isor` high
        #10;

        // Test AND operation
        alusignals = 12'b000000100000; // Setting `isand` high
        #10;

        // Test NOT operation
        alusignals = 12'b000001000000; // Setting `isnot` high
        op1 = 16'hFFFF; // Test with all 1s to check NOT
        #10;

        // Test immediate mode for MOV
        alusignals = 12'b000010000000; // Setting `ismov` high
        isimmediate = 1;  // Immediate mode
        immx = 5'b00101;  // Set immediate value
        #10;

        // Test LSL (Logical Shift Left)
        alusignals = 12'b000100000000; // Setting `islsl` high
        op1 = 16'h0001;
        op2 = 16'h0003; // Shift left by 3
        #10;

        // Test LSR (Logical Shift Right)
        alusignals = 12'b001000000000; // Setting `islsr` high
        op1 = 16'h0008;
        op2 = 16'h0002; // Shift right by 2
        #10;

        // Test CMP (Compare)
        alusignals = 12'b000000100000; // Setting `iscmp` high
        op1 = 16'h000A;
        op2 = 16'h000A; // Compare equal case
        #10;

        // Test invalid operation
        alusignals = 12'b000000000000; // No operation selected
        #10;

        $finish;  // End of simulation
    end

endmodule

alu_tb.vcd
$date
	Sun Nov 10 06:32:18 2024
$end
$version
	Icarus Verilog
$end
$timescale
	1s
$end
$scope module alu_tb $end
$var wire 19 ! rdval [18:0] $end
$var wire 16 " aluresult [15:0] $end
$var reg 12 # alusignals [11:0] $end
$var reg 1 $ clk $end
$var reg 5 % immx [4:0] $end
$var reg 16 & instr [15:0] $end
$var reg 1 ' isimmediate $end
$var reg 16 ( op1 [15:0] $end
$var reg 16 ) op2 [15:0] $end
$scope module uut $end
$var wire 16 * aluresult [15:0] $end
$var wire 12 + alusignals [11:0] $end
$var wire 1 $ clk $end
$var wire 5 , immx [4:0] $end
$var wire 16 - instr [15:0] $end
$var wire 1 ' isimmediate $end
$var wire 16 . op1 [15:0] $end
$var wire 16 / op2 [15:0] $end
$var wire 19 0 rdval [18:0] $end
$var wire 1 1 issub $end
$var wire 1 2 isst $end
$var wire 1 3 isor $end
$var wire 1 4 isnot $end
$var wire 1 5 ismul $end
$var wire 1 6 ismov $end
$var wire 1 7 islsr $end
$var wire 1 8 islsl $end
$var wire 1 9 isld $end
$var wire 1 : iscmp $end
$var wire 1 ; isand $end
$var wire 1 < isadd $end
$var reg 16 = A [15:0] $end
$var reg 16 > B [15:0] $end
$var reg 5 ? immx_reg [4:0] $end
$var reg 16 @ instrw [15:0] $end
$var reg 1 A isadd_reg $end
$var reg 1 B isand_reg $end
$var reg 1 C iscmp_reg $end
$var reg 1 D isimmediate_reg $end
$var reg 1 E isld_reg $end
$var reg 1 F islsl_reg $end
$var reg 1 G islsr_reg $end
$var reg 1 H ismov_reg $end
$var reg 1 I ismul_reg $end
$var reg 1 J isnot_reg $end
$var reg 1 K isor_reg $end
$var reg 1 L isst_reg $end
$var reg 1 M issub_reg $end
$var reg 16 N op1_reg [15:0] $end
$var reg 16 O op2_reg [15:0] $end
$var reg 3 P rd [2:0] $end
$var reg 16 Q result [15:0] $end
$var integer 32 R file [31:0] $end
$var integer 32 S i [31:0] $end
$upscope $end
$upscope $end
$enddefinitions $end
#0
$dumpvars
bx S
bx R
bx Q
b0 P
b0 O
b0 N
0M
0L
0K
0J
0I
0H
0G
0F
0E
0D
0C
0B
0A
b0 @
b0 ?
bx >
bx =
x<
x;
x:
x9
x8
x7
x6
x5
x4
x3
x2
x1
bx000 0
bx /
bx .
bx -
bx ,
bx +
bx *
bx )
bx (
x'
bx &
bx %
0$
bx #
bx "
bx000 !
$end
#5
xG
xF
xJ
xB
xK
xH
xC
xI
xM
xL
xE
xA
b0 !
b0 0
b0 "
b0 *
b0 Q
0<
09
02
01
05
0:
06
03
0;
04
08
07
b0 >
b0 =
0'
b0 &
b0 -
b0 %
b0 ,
b0 )
b0 /
b0 (
b0 .
b0 #
b0 +
1$
#10
0$
#15
b101 O
b10000 N
0G
0F
0J
0B
0K
0H
0C
0I
0M
0L
0E
1A
b101 >
b10000 =
1<
1$
b1 #
b1 +
b101 )
b101 /
b10000 (
b10000 .
#20
0$
#25
1E
0A
b10101000 !
b10101000 0
b10101 "
b10101 *
b10101 Q
0<
19
1$
b10 #
b10 +
#30
0$
#35
1M
0E
09
11
1$
b1000 #
b1000 +
#40
0$
#45
1I
0M
b1011000 !
b1011000 0
b1011 "
b1011 *
b1011 Q
01
15
1$
b10000 #
b10000 +
#50
0$
#55
1C
0I
b1010000000 !
b1010000000 0
b1010000 "
b1010000 *
b1010000 Q
05
1:
1$
b100000 #
b100000 +
#60
0$
#65
b1111111111111111 N
1H
0C
b0 !
b0 0
b0 "
b0 *
b0 Q
b1000 S
b10000000000000000000000000000011 R
b1111111111111111 =
0:
16
1$
b1111111111111111 (
b1111111111111111 .
b1000000 #
b1000000 +
#70
0$
#75
1D
1K
0H
b101000 !
b101000 0
b101 "
b101 *
b101 Q
06
13
1$
b101 %
b101 ,
1'
b10000000 #
b10000000 +
#80
0$
#85
b11 O
b1 N
1B
0K
b1 =
03
1;
1$
b11 )
b11 /
b1 (
b1 .
b100000000 #
b100000000 +
#90
0$
#95
b10 O
b1000 N
1J
0B
b0 !
b0 0
b0 "
b0 *
b0 Q
b1000 =
0;
14
1$
b10 )
b10 /
b1000 (
b1000 .
b1000000000 #
b1000000000 +
#100
0$
#105
b1010 O
b1010 N
0J
1C
b1111111111110101000 !
b1111111111110101000 0
b1111111111110101 "
b1111111111110101 *
b1111111111110101 Q
b1010 =
1:
04
1$
b1010 )
b1010 /
b1010 (
b1010 .
b100000 #
b100000 +
#110
0$
#115
0C
b0 !
b0 0
b0 "
b0 *
b0 Q
b1000 S
0:
1$
b0 #
b0 +
