src/fetch/fetch_unit.v
module fetch_unit (
    input wire clk,
    input wire reset,
    input wire stall,                                                 
    input wire is_branch_taken,                  // Signal that branch is taken
    input wire [31:0] branch_target,          // Branch target address
    output reg [31:0] instr1,                 // First instruction for decode
    output reg [31:0] instr2                  // Second instruction for decode
);

    reg [31:0] pc;                            // Program Counter
    reg [31:0] instruction_memory [0:10];    // Instruction memory (single-port)
    reg [31:0] buffer [1:0];                  // 2-entry instruction buffer

    // Initialize instruction memory (for simulation)
    initial begin
        $readmemh("instructions.hex", instruction_memory);
    end
    reg flush = 0;
    // PC update logic with branch handling and buffer control
    always @(posedge clk or posedge reset) begin
        if (reset) begin
            pc <= 0;
            buffer[0] <= 0;
            buffer[1] <= 0;
        end else if (is_branch_taken) begin
            pc <= branch_target;               // On branch, set PC to branch target
            buffer[0] <= 0;                     // instead of 0 place the nop instruction
            buffer[1] <= 0;                     // instead of 0 place the nop instruction
            flush <= 1;
        end else if (flush) begin
            buffer[0] <= 0;                     // instead of 0 place the nop instruction
            buffer[1] <= 0;                     // instead of 0 place the nop instruction
            flush <= 0;
        end else if (stall) begin 
            buffer[0] <= 0; // Fetch to buffer[0]
            buffer[1] <= 0; // Fetch to buffer[1]
        end else if (!stall) begin
            buffer[0] <= instruction_memory[pc]; // Fetch to buffer[0]
            buffer[1] <= instruction_memory[pc+1]; // Fetch to buffer[1]
            pc <= pc + 2;
        end
    end
    // Output instructions from buffer to decode stage
    always @(*) begin
        if(stall) begin
            instr1 = 0;   // replace with nop
            instr2 = 0;  // replace with nop    
        end
        else begin
            instr1 = buffer[0];
            instr2 = buffer[1];
        end
    end

endmodule

tb/fetch_unit_tb.v
module tb_fetch_unit;

    // Testbench signals
    reg clk;
    reg reset;
    reg stall;
    reg is_branch_taken;
    reg [31:0] branch_target;
    wire [31:0] instr1;
    wire [31:0] instr2;
    reg [31:0] pc;
    // Instantiate the fetch unit
    fetch_unit uut (
        .clk(clk),
        .reset(reset),
        .stall(stall),
        .is_branch_taken(is_branch_taken),
        .branch_target(branch_target),
        .instr1(instr1),
        .instr2(instr2)
    );

    // Initialize all signals
    initial begin
        $dumpfile("fetch_unit.vcd");
        $dumpvars(0,tb_fetch_unit);
        clk = 0;
        reset = 0;
        stall = 0;
        is_branch_taken = 0;
        branch_target = 0;

        // Apply reset
        #5 reset = 1;
        #10 reset = 0;
        // Run test scenarios
        test_no_branch;
        // #10 test_stall;
        #10 test_no_branch;
        #10 test_with_branch;
        #10 test_no_branch;
        #50 $finish;
    end

    // Clock generation
    always begin
        #5 clk = ~clk;  // Toggle clock every 5 time units
    end

    // Test Case 1: No Branch, Normal Fetch
    task test_no_branch;
        begin
            // Test fetching two instructions without a branch
            is_branch_taken = 0;
            branch_target = 32'h0;
            stall = 0;

            // Observe the outputs
            // #20; // Wait for a few clock cycles
            $display("instr1: %h, instr2: %h", instr1, instr2);
        end
    endtask

    // Test Case 2: Branch Taken, Reset PC
    task test_with_branch;
        begin
            // Test fetching with a branch taken
            is_branch_taken = 1;
            branch_target = 32'h5; // Set branch target to a new address
            stall = 0;

            // Observe the outputs after branch handling
            // #20; // Wait for a few clock cycles
            $display("After branch, instr1: %h, instr2: %h", instr1, instr2);
        end
    endtask

    // Test Case 3: Stall the Fetch
    task test_stall;
        begin
            // Test with the stall signal active
            stall = 1;
            is_branch_taken = 0;
            branch_target = 32'h0;
            reset = 0;

            // No new fetch should occur due to stall
            #10; // Wait for a few clock cycles
            $display("Stalled, instr1: %h, instr2: %h", instr1, instr2);
        end
    endtask

endmodule

fetch_unit.vcd
$date
	Fri Nov  8 05:41:55 2024
$end
$version
	Icarus Verilog
$end
$timescale
	1s
$end
$scope module tb_fetch_unit $end
$var wire 32 ! instr2 [31:0] $end
$var wire 32 " instr1 [31:0] $end
$var reg 32 # branch_target [31:0] $end
$var reg 1 $ clk $end
$var reg 1 % is_branch_taken $end
$var reg 1 & reset $end
$var reg 1 ' stall $end
$scope module uut $end
$var wire 32 ( branch_target [31:0] $end
$var wire 1 $ clk $end
$var wire 1 % is_branch_taken $end
$var wire 1 & reset $end
$var wire 1 ' stall $end
$var reg 1 ) flush $end
$var reg 32 * instr1 [31:0] $end
$var reg 32 + instr2 [31:0] $end
$var reg 32 , pc [31:0] $end
$upscope $end
$scope task test_no_branch $end
$upscope $end
$scope task test_stall $end
$upscope $end
$scope task test_with_branch $end
$upscope $end
$upscope $end
$enddefinitions $end
#0
$dumpvars
bx ,
bx +
bx *
0)
b0 (
0'
0&
0%
0$
b0 #
bx "
bx !
$end
#5
b0 !
b0 +
b0 "
b0 *
b0 ,
1$
1&
#10
0$
#15
b10 !
b10 +
b1 "
b1 *
b10 ,
1$
0&
#20
0$
#25
b100 !
b100 +
b11 "
b11 *
b100 ,
1$
#30
0$
#35
b0 !
b0 +
b0 "
b0 *
1)
b101 ,
1$
b101 #
b101 (
1%
#40
0$
#45
0)
1$
b0 #
b0 (
0%
#50
0$
#55
b111 !
b111 +
b110 "
b110 *
b111 ,
1$
#60
0$
#65
b1001 !
b1001 +
b1000 "
b1000 *
b1001 ,
1$
#70
0$
#75
b10001 !
b10001 +
b10000 "
b10000 *
b1011 ,
1$
#80
0$
#85
bx !
bx +
bx "
bx *
b1101 ,
1$
#90
0$
#95
b1111 ,
1$
