src/fetch/fetch_unit.v
module fetch_unit (
    input wire clk,
    input wire reset,
    input wire stall,
    input wire is_branch_taken,               // Signal that branch is taken
    input wire [15:0] branch_target,          // Branch target address
    input wire issingleinstr,
    output wire [15:0] instr1,                // First instruction for decode
    output wire [15:0] instr2                 // Second instruction for decode
);
    reg [15:0] pc;                            // Program Counter
    reg [15:0] instruction_memory [0:10];     // Instruction memory (single-port)
    reg [15:0] buffer [1:0];                  // 2-entry instruction buffer to hold current instructions
    reg [15:0] instr1_reg;
    reg [15:0] instr2_reg;

    // Initialize instruction memory and buffer (for simulation)
    initial begin
        $readmemh("instructions.hex", instruction_memory);
        buffer[0] = instruction_memory[0];    // Load first instruction
        buffer[1] = instruction_memory[1];    // Load second instruction
        instr1_reg = 16'h0;
        instr2_reg = 16'h0;
    end

    // PC update logic with branch handling and buffer control
    always @(posedge clk or posedge reset) begin
        if (reset) begin
            // On reset, clear PC and buffer
            pc = 0;
            buffer[0] = 16'b0; // Initialize buffer with first instruction
            buffer[1] = 16'b0; // Initialize buffer with second instruction
            instr1_reg = 16'h0;
            instr2_reg = 16'h0;
        end 
        else if (is_branch_taken) begin
            // If branch is taken, set PC to branch target and flush buffer
            pc = branch_target;
            buffer[0] = 16'h0; // NOP for buffer
            buffer[1] = 16'h0; // NOP for buffer
        end
        else if (stall) begin 
            // If stalled, hold current buffer values (instructions)
            buffer[0] = buffer[0];
            buffer[1] = buffer[1];
        end 
        else begin
            // Fetch two instructions into buffer on each cycle
            if (!issingleinstr) begin
                buffer[0] = instruction_memory[pc];       // Fetch instruction at PC
                buffer[1] = instruction_memory[pc + 1];   // Fetch next instruction
                pc = pc + 2;                              // Increment PC by 2 for 2 instructions
            end else begin
                buffer[0] = instruction_memory[pc];       // Fetch instruction at PC
                buffer[1] = 16'h0;                        // NOP for buffer
                pc = pc + 1;                              // Increment PC by 1 for 1 instruction
            end
        end

        // Update instr1 and instr2 with buffer values from previous cycle (next-cycle update)
        if (!stall) begin
            instr1_reg = buffer[0];
            instr2_reg = buffer[1];
        end
        else begin
            instr1_reg = 16'h0;
            instr2_reg = 16'h0;
        end
    end

    assign instr1 = instr1_reg;
    assign instr2 = instr2_reg;

endmodule

tb/fetch_unit_tb.v
module tb_fetch_unit;

    // Testbench signals
    reg clk;
    reg reset;
    reg stall;
    reg is_branch_taken;
    reg [15:0] branch_target;
    wire [15:0] instr1;
    wire [15:0] instr2;
    reg [15:0] pc;
    // Instantiate the fetch unit
    fetch_unit uut (
        .clk(clk),
        .reset(reset),
        .stall(stall),
        .is_branch_taken(is_branch_taken),
        .branch_target(branch_target),
        .instr1(instr1),
        .instr2(instr2)
    );

    // Initialize all signals
    initial begin
        $dumpfile("fetch_unit.vcd");
        $dumpvars(0,tb_fetch_unit);
        clk = 0;
        reset = 0;
        stall = 0;
        is_branch_taken = 0;
        branch_target = 0;

        // Apply reset
        #5 reset = 1;
        #10 reset = 0;
        // Run test scenarios
        test_no_branch;
        // #10 test_stall;
        #10 test_no_branch;
        #10 test_with_branch;
        #10 test_no_branch;
        #50 $finish;
    end

    // Clock generation
    always begin
        #5 clk = ~clk;  // Toggle clock every 5 time units
    end

    // Test Case 1: No Branch, Normal Fetch
    task test_no_branch;
        begin
            // Test fetching two instructions without a branch
            is_branch_taken = 0;
            branch_target = 16'h0;
            stall = 0;

            // Observe the outputs
            // #20; // Wait for a few clock cycles
            $display("instr1: %h, instr2: %h", instr1, instr2);
        end
    endtask

    // Test Case 2: Branch Taken, Reset PC
    task test_with_branch;
        begin
            // Test fetching with a branch taken
            is_branch_taken = 1;
            branch_target = 16'h5; // Set branch target to a new address
            stall = 0;

            // Observe the outputs after branch handling
            // #20; // Wait for a few clock cycles
            $display("After branch, instr1: %h, instr2: %h", instr1, instr2);
        end
    endtask

    // Test Case 3: Stall the Fetch
    task test_stall;
        begin
            // Test with the stall signal active
            stall = 1;
            is_branch_taken = 0;
            branch_target = 16'h0;
            reset = 0;

            // No new fetch should occur due to stall
            #10; // Wait for a few clock cycles
            $display("Stalled, instr1: %h, instr2: %h", instr1, instr2);
        end
    endtask

endmodule

fetch_unit.vcd
$date
	Sun Nov 10 01:28:12 2024
$end
$version
	Icarus Verilog
$end
$timescale
	1s
$end
$scope module tb_fetch_unit $end
$var wire 16 ! instr2 [15:0] $end
$var wire 16 " instr1 [15:0] $end
$var reg 16 # branch_target [15:0] $end
$var reg 1 $ clk $end
$var reg 1 % is_branch_taken $end
$var reg 1 & reset $end
$var reg 1 ' stall $end
$scope module uut $end
$var wire 16 ( branch_target [15:0] $end
$var wire 1 $ clk $end
$var wire 16 ) instr1 [15:0] $end
$var wire 16 * instr2 [15:0] $end
$var wire 1 % is_branch_taken $end
$var wire 1 + issingleinstr $end
$var wire 1 & reset $end
$var wire 1 ' stall $end
$var reg 16 , instr1_reg [15:0] $end
$var reg 16 - instr2_reg [15:0] $end
$var reg 16 . pc [15:0] $end
$upscope $end
$scope task test_no_branch $end
$upscope $end
$scope task test_stall $end
$upscope $end
$scope task test_with_branch $end
$upscope $end
$upscope $end
$enddefinitions $end
#0
$dumpvars
bx .
b0 -
b0 ,
z+
b0 *
b0 )
b0 (
0'
0&
0%
0$
b0 #
b0 "
b0 !
$end
#5
b0 .
1$
1&
#10
0$
#15
b1 .
1$
0&
#20
0$
#25
b1 "
b1 )
b1 ,
b10 .
1$
#30
0$
#35
b10 "
b10 )
b10 ,
b101 .
1$
b101 #
b101 (
1%
#40
0$
#45
b0 "
b0 )
b0 ,
b110 .
1$
b0 #
b0 (
0%
#50
0$
#55
b110 "
b110 )
b110 ,
b111 .
1$
#60
0$
#65
b111 "
b111 )
b111 ,
b1000 .
1$
#70
0$
#75
b1000 "
b1000 )
b1000 ,
b1001 .
1$
#80
0$
#85
b1001 "
b1001 )
b1001 ,
b1010 .
1$
#90
0$
#95
b10000 "
b10000 )
b10000 ,
b1011 .
1$
