src/memory/memory_unit.v
module memory_unit (
    input wire clk,
    input wire isld,
    input wire isst,
    input wire [15:0] instr,
    input wire [15:0] op2,
    input wire [15:0] aluresult,
    output wire [15:0] ldresult,
    output wire [18:0] rdvalmem
);
    integer i;
    reg [15:0] memory[0:31]; // Memory array to hold values from hex file , 32 addressess and 16 bit data
    initial begin
        $readmemh("data_memory.hex", memory);
        ld_reg = 16'h0000;
        ld = 16'h0000;
        rd = 4'h0;   
        instr_rd = 4'h0;  
    end
    integer file;
    reg [15:0] ld_reg,ld;
    reg [3:0] rd;
    reg [3:0] instr_rd;
    always @(posedge clk) begin
        if (isld) begin
            $readmemh("data_memory.hex", memory);
            ld_reg <= memory[aluresult];
            $display("ldresult_reg = %h", ld_reg);
        end
        else if (isst) begin
            $readmemh("data_memory.hex", memory);
            file = $fopen("data_memory.hex", "w");
            memory[aluresult] = op2;
            for (i = 0; i < 32; i = i + 1) begin
                $fwrite(file, "%h\n", memory[i]); 
            end
            ld_reg <= 16'h0000;
            $fclose(file);
        end
        else begin 
            ld_reg <= 16'h0000;
        end
        $display("ldresult = %h", ld);
        ld <= ld_reg;
        instr_rd <= instr[7:4];
        rd <= instr_rd;
    end
    assign ldresult = ld;
    assign rdvalmem = {ld,rd};
endmodule

tb/memory_unit_tb.v

module memory_unit_tb;
    reg clk;
    reg isld;
    reg isst;
    reg [15:0] instr;
    reg [15:0] op2;
    reg [15:0] aluresult;
    wire [15:0] ldresult;
    wire [18:0] rdvalmem;

    // Instantiate the memory unit
    memory_unit uut (
        .clk(clk),
        .isld(isld),
        .isst(isst),
        .instr(instr),
        .op2(op2),
        .aluresult(aluresult),
        .ldresult(ldresult),
        .rdvalmem(rdvalmem)
    );

    // Clock generation
    initial begin
        clk = 0;
        forever #5 clk = ~clk;  // Toggle clock every 5 ns
    end

    // Initialize memory file and set up initial conditions
    initial begin
        $dumpfile("memory_unit.vcd");
        $dumpvars(0, memory_unit_tb);
        // Initialize control signals
        #5; 
        isld = 0;
        isst = 0;
        instr = 16'b0;
        op2 = 16'b0;
        aluresult = 16'b0;

        // Initial reset state to read memory
        $display("Starting memory unit test...");

        // Test load operation
        #10;
        aluresult = 16'h0002;  // Address to load from
        isld = 1;
        isst = 0;
        #10;
        isld = 0;
        $display("Loaded data at address 0x0002: ldresult = %h, rdvalmem = %h", ldresult, rdvalmem);

        // Test store operation
        #10;
        aluresult = 16'h0003;  // Address to store to
        op2 = 16'hABCD;       // Data to store
        isst = 1;
        isld = 0;
        #10;
        isst = 0;
        $display("Stored data 0xABCD at address 0x0003");

        // Verify if the data was stored correctly by loading it back
        #10;
        aluresult = 16'h0003;
        isld = 1;
        isst = 0;
        #10;
        isld = 0;
        $display("Loaded data at address 0x0003 after store: ldresult = %h, rdvalmem = %h", ldresult, rdvalmem);

        // Add more test cases as needed
        $finish;    
    end
endmodule

memory_unit.vcd
$date
	Sun Nov 10 07:03:18 2024
$end
$version
	Icarus Verilog
$end
$timescale
	1s
$end
$scope module memory_unit_tb $end
$var wire 19 ! rdvalmem [18:0] $end
$var wire 16 " ldresult [15:0] $end
$var reg 16 # aluresult [15:0] $end
$var reg 1 $ clk $end
$var reg 16 % instr [15:0] $end
$var reg 1 & isld $end
$var reg 1 ' isst $end
$var reg 16 ( op2 [15:0] $end
$scope module uut $end
$var wire 16 ) aluresult [15:0] $end
$var wire 1 $ clk $end
$var wire 16 * instr [15:0] $end
$var wire 1 & isld $end
$var wire 1 ' isst $end
$var wire 16 + ldresult [15:0] $end
$var wire 16 , op2 [15:0] $end
$var wire 19 - rdvalmem [18:0] $end
$var reg 4 . instr_rd [3:0] $end
$var reg 16 / ld [15:0] $end
$var reg 16 0 ld_reg [15:0] $end
$var reg 4 1 rd [3:0] $end
$var integer 32 2 file [31:0] $end
$var integer 32 3 i [31:0] $end
$upscope $end
$upscope $end
$enddefinitions $end
#0
$dumpvars
bx 3
bx 2
b0 1
b0 0
b0 /
b0 .
b0 -
bx ,
b0 +
bx *
bx )
bx (
x'
x&
bx %
0$
bx #
b0 "
b0 !
$end
#5
b0 #
b0 )
b0 (
b0 ,
b0 %
b0 *
0'
0&
1$
#10
0$
#15
b11 0
1$
1&
b10 #
b10 )
#20
0$
#25
b110000 !
b110000 -
b11 "
b11 +
b11 /
b0 0
1$
0&
#30
0$
#35
b0 !
b0 -
b0 "
b0 +
b0 /
b100000 3
b10000000000000000000000000000011 2
1$
1'
b1010101111001101 (
b1010101111001101 ,
b11 #
b11 )
#40
0$
#45
1$
0'
#50
0$
#55
b1010101111001101 0
1$
1&
#60
0$
#65
b0 0
1$
0&
