src/memory/memory_unit.v
module memory_unit (
    input wire clk,
    input wire isld,
    input wire isst,
    input wire reset,
    input wire iswb,
    input wire [15:0] instr,
    input wire [15:0] op2,
    input wire [15:0] aluresult,
    output wire [15:0] aluresult_out,
    output wire isld_out,
    output wire iswb_out,
    output wire [15:0] instr_out,
    output wire [15:0] ldresult,
    output wire [19:0] rdvalmem
);
    integer i;
    reg [15:0] aluresult_reg;
    reg [15:0] instr_rd;
    reg [15:0] instr_1;
    reg iswb_1;
    reg iswb_reg;
    reg isld_reg;
    reg isld_1;
    reg [15:0] memory[0:31]; // Memory array to hold values from hex file , 32 addressess and 16 bit data
    initial begin
        $readmemh("data_memory.hex", memory);
        ld_reg = 16'h0000;
        ld = 16'h0000;
        aluresult_reg = 16'h0000;
        result = 19'h00000;
        rdval = 19'h00000;
    end
    integer file;
    reg [15:0] ld_reg,ld;
    reg [19:0] result;
    reg [19:0] rdval;
    always @(posedge clk) begin
        if(reset) begin
            ld_reg <= 16'h0;
            result <= 19'h0;
            aluresult_reg <= 16'h0;
        end
        else if (isld) begin
            $readmemh("data_memory.hex", memory);
            ld_reg <= memory[aluresult];
            $readmemh("data_memory.hex", memory);
            result <= {1'h0,memory[aluresult],instr[10:8]};
            // $display("rdval = %h", result);
        end
        else if (isst) begin
            $readmemh("data_memory.hex", memory);
            file = $fopen("data_memory.hex", "w");
            memory[aluresult] = op2;
            for (i = 0; i < 32; i = i + 1) begin
                $fwrite(file, "%h\n", memory[i]); 
            end
            ld_reg <= 16'h0000;
            $fclose(file);
            result <= {19'h0,1'h1};
            // $display("rdval = %h", result);
        end
        else begin 
            ld_reg <= 16'h0000;
            // result_1 = {aluresult, instr[7:5]};
            result <={instr[10:8],aluresult,1'h0};
            // $display("rdval = %h", result);x
        end
        // $display("ldresult = %h", ld);
        aluresult_reg<=aluresult;
        $display("aluresult: ", aluresult);
        $display("aluresult_reg: ", aluresult_reg);
        ld<=ld_reg;
        rdval<=result;
        isld_1<=isld;
        isld_reg<=isld_1;
        iswb_reg<=iswb;
        iswb_1<=iswb_reg;
        instr_rd<=instr;
        instr_1<=instr_rd;
    end
    assign ldresult = ld;
    assign rdvalmem = result;
    assign aluresult_out = aluresult_reg;
    assign iswb_out = iswb_reg;
    assign instr_out = instr_rd;
    assign isld_out = isld_reg;
endmodule

tb/memory_unit_tb.v

module memory_unit_tb;
    // Testbench signals
    reg clk;
    reg isld;
    reg isst;
    reg [15:0] op2;
    reg [15:0] aluresult;
    wire [15:0] ldresult;

    // Instantiate the memory_unit module
    memory_unit dut (
        .clk(clk),
        .isld(isld),
        .isst(isst),
        .op2(op2),
        .aluresult(aluresult),
        .ldresult(ldresult)
    );

    // Clock generation
    initial begin
        clk = 0;
        forever #5 clk = ~clk; // Toggle clock every 5 ns for a 10 ns period
    end

    // Test sequence
    initial begin
        // Initialize control signals
        $dumpfile("memory_unit.vcd");
        $dumpvars(0, memory_unit_tb);
        isld = 0;
        isst = 0;
        op2 = 16'h0000;
        aluresult = 16'h0000;

        // Display initial message
        $display("Starting memory_unit testbench...");

        // Wait for the initial clock cycle
        #10;

        // Test store operation
        $display("Testing store operation...");
        isst = 1;
        aluresult = 16'h0001; // Address to store at
        op2 = 16'hA5A5;       // Data to store
        #10;
        isst = 0; // End of store operation

        // Wait for a clock cycle, then test load operation
        #10;
        $display("Testing load operation...");
        isld = 1;
        aluresult = 16'h0001; // Address to load from
        #10;
        isld = 0; // End of load operation

        // Observe output in the next clock cycle
        #10;
        $display("Expected load result: A5A5, Actual ldresult: %h", ldresult);

        // Test store operation at a different address
        $display("Testing store operation at a different address...");
        #10;
        isst = 1;
        aluresult = 16'h0002; // Address to store at
        op2 = 16'h5A5A;       // Data to store
        #10;
        isst = 0; // End of store operation

        // Load from the new address
        #10;
        isld = 1;
        aluresult = 16'h0002; // Address to load from
        #10;
        isld = 0; // End of load operation

        // Observe output in the next clock cycle
        #10;
        $display("Expected load result: 5A5A, Actual ldresult: %h", ldresult);

        // End of simulation
        #10;
        $finish;
    end
endmodule

memory_unit.vcd
$date
	Sat Nov  9 21:54:40 2024
$end
$version
	Icarus Verilog
$end
$timescale
	1s
$end
$scope module memory_unit_tb $end
$var wire 16 ! ldresult [15:0] $end
$var reg 16 " aluresult [15:0] $end
$var reg 1 # clk $end
$var reg 1 $ isld $end
$var reg 1 % isst $end
$var reg 16 & op2 [15:0] $end
$scope module dut $end
$var wire 16 ' aluresult [15:0] $end
$var wire 1 # clk $end
$var wire 1 $ isld $end
$var wire 1 % isst $end
$var wire 16 ( ldresult [15:0] $end
$var wire 16 ) op2 [15:0] $end
$var reg 16 * ld [15:0] $end
$var reg 16 + ld_reg [15:0] $end
$var integer 32 , file [31:0] $end
$var integer 32 - i [31:0] $end
$upscope $end
$upscope $end
$enddefinitions $end
#0
$dumpvars
bx -
bx ,
b0 +
b0 *
b0 )
b0 (
b0 '
b0 &
0%
0$
0#
b0 "
b0 !
$end
#5
1#
#10
0#
b1010010110100101 &
b1010010110100101 )
b1 "
b1 '
1%
#15
b100000 -
b10000000000000000000000000000011 ,
1#
#20
0#
0%
#25
1#
#30
0#
1$
#35
b1010010110100101 +
1#
#40
0#
0$
#45
1#
b1010010110100101 !
b1010010110100101 (
b1010010110100101 *
#50
0#
#55
1#
#60
0#
b101101001011010 &
b101101001011010 )
b10 "
b10 '
1%
#65
b0 +
b100000 -
1#
#70
0#
0%
#75
1#
b0 !
b0 (
b0 *
#80
0#
1$
#85
b101101001011010 +
1#
#90
0#
0$
#95
1#
b101101001011010 !
b101101001011010 (
b101101001011010 *
